qobra/__init__.py
qobra/aidees.py
qobra/config.py
qobra/player.py
qobra/qobra.py
qobra/searchbox.py
qobra/song.py
qobra/window.py
qobra-1.1.1.dist-info/LICENSE
qobra-1.1.1.dist-info/METADATA
qobra-1.1.1.dist-info/WHEEL
qobra-1.1.1.dist-info/entry_points.txt
qobra-1.1.1.dist-info/top_level.txt
qobra-1.1.1.dist-info/RECORD
