Metadata-Version: 2.1
Name: qobra
Version: 1.1.1
Summary: A simple music player for the command line
Home-page: https://github.com/aloussase/qobra
Author: Alexander Goussas
Author-email: agoussas@espol.edu.ec
License: UNKNOWN
Platform: UNKNOWN
Classifier: Programming Language :: Python :: 3
Classifier: License :: OSI Approved :: GNU General Public License v3 (GPLv3)
Requires-Python: >=3.6
